pandadocs/__init__.py
pandadocs/api.py
pandadocs/tool.py
pandadocs-0.1.2.dist-info/DESCRIPTION.rst
pandadocs-0.1.2.dist-info/METADATA
pandadocs-0.1.2.dist-info/RECORD
pandadocs-0.1.2.dist-info/WHEEL
pandadocs-0.1.2.dist-info/entry_points.txt
pandadocs-0.1.2.dist-info/metadata.json
pandadocs-0.1.2.dist-info/top_level.txt
