Metadata-Version: 2.0
Name: pandadocs
Version: 0.1.2
Summary: Easy pythonic integration with Pandadocs' REST API
Home-page: https://bitbucket.com/alokinplc/pandadocs/
Author: Alokin Software Pvt Ltd
Author-email: rajeev@alokin.in
License: MIT license
Keywords: pandadocs
Platform: UNKNOWN
Classifier: Development Status :: 2 - Pre-Alpha
Classifier: Intended Audience :: Developers
Classifier: License :: OSI Approved :: MIT License
Classifier: Natural Language :: English
Classifier: Programming Language :: Python :: 2.7
Requires-Dist: purl (==1.3)
Requires-Dist: requests-oauthlib (==0.6.1)
